{
    "TotalCount": 62,
    "HierarchicalData": [
        {
            "TotalCount": 30,
            "Name": "Late",
            "Level": 0
        },
        {
            "Id": "44844501-9184-447e-bee0-f1c9caf483c3",
            "Level": 1,
            "Type": "Task",
            "WorkItemId": "f7c4552e-a617-4b7f-bfc1-0d9043fb6627",
            "Title": "Task for notification 111",
            "Client": null,
            "PlannedDate": "2020-10-14T00:00:00.000Z",
            "PlannedStartTime": null,
            "PlannedEndTime": null,
            "PlannedWorkload": 0.25,
            "Timesheets": 0.5,
            "Status": "Planned",
            "Color": null
        },
        {
            "Id": "e4ba5de7-a156-48df-b18c-af43821cd30f",
            "Level": 1,
            "Type": "Task",
            "WorkItemId": "5eb581ab-53dd-49d1-8ecc-0ce466513521",
            "Title": "Add from Angular",
            "Client": null,
            "PlannedDate": "2020-10-15T00:00:00.000Z",
            "PlannedStartTime": null,
            "PlannedEndTime": null,
            "PlannedWorkload": 5,
            "Timesheets": 0,
            "Status": "Completed",
            "Color": "#304100"
        },
        {
            "Id": "549aebfb-74ff-4b63-8e5e-4de439b86ac0",
            "Level": 1,
            "Type": "Task",
            "WorkItemId": "f7c4552e-a617-4b7f-bfc1-0d9043fb6627",
            "Title": "Task for notification 111",
            "Client": null,
            "PlannedDate": "2020-11-17T00:00:00.000Z",
            "PlannedStartTime": null,
            "PlannedEndTime": null,
            "PlannedWorkload": 0.25,
            "Timesheets": 0,
            "Status": "InProgress",
            "Color": null
        },
        {
            "Id": "3f1dfa1e-f4c3-4fea-9731-a6cc4a3f259f",
            "Level": 1,
            "Type": "Intervention",
            "WorkItemId": "55dcadd9-7d79-47e5-a625-0bbb38e18075",
            "Title": "40.3: Test GF-161 with job and client",
            "Client": null,
            "PlannedDate": "2020-11-25T00:00:00.000Z",
            "PlannedStartTime": null,
            "PlannedEndTime": null,
            "PlannedWorkload": 0.25,
            "Timesheets": 0,
            "Status": "Completed",
            "Color": "#304100"
        },
        {
            "Id": "7269aecd-6b4c-4955-b571-e9e4fc58f5cf",
            "Level": 1,
            "Type": "Intervention",
            "WorkItemId": "55dcadd9-7d79-47e5-a625-0bbb38e18075",
            "Title": "40.3: Test GF-161 with job and client",
            "Client": null,
            "PlannedDate": "2020-12-03T00:00:00.000Z",
            "PlannedStartTime": null,
            "PlannedEndTime": null,
            "PlannedWorkload": 6,
            "Timesheets": 0,
            "Status": "Planned",
            "Color": "#304100"
        },
        {
            "Id": "6ecf9dba-8427-4ba7-ad13-bb211fdd36dc",
            "Level": 1,
            "Type": "Intervention",
            "WorkItemId": "55dcadd9-7d79-47e5-a625-0bbb38e18075",
            "Title": "40.3: Test GF-161 with job and client",
            "Client": null,
            "PlannedDate": "2020-12-04T00:00:00.000Z",
            "PlannedStartTime": null,
            "PlannedEndTime": null,
            "PlannedWorkload": 3.25,
            "Timesheets": 0,
            "Status": "Cancelled",
            "Color": "#304100"
        },
        {
            "Id": "674d65b4-9bdf-4b80-812e-f4d945ff294e",
            "Level": 1,
            "Type": "Task",
            "WorkItemId": "1d98f5f7-4034-457c-892e-376d86fd978f",
            "Title": "Task 2",
            "Client": null,
            "PlannedDate": "2020-12-10T00:00:00.000Z",
            "PlannedStartTime": null,
            "PlannedEndTime": null,
            "PlannedWorkload": 4,
            "Timesheets": 0,
            "Status": "Requested",
            "Color": null
        },
        {
            "Id": "036f2067-f1e4-4cc9-a6fe-0db063958353",
            "Level": 1,
            "Type": "Task",
            "WorkItemId": "1d98f5f7-4034-457c-892e-376d86fd978f",
            "Title": "Task 2",
            "Client": null,
            "PlannedDate": "2020-12-15T00:00:00.000Z",
            "PlannedStartTime": null,
            "PlannedEndTime": null,
            "PlannedWorkload": 2.5,
            "Timesheets": 0,
            "Status": "Requested",
            "Color": null
        },
        {
            "Id": "b797e42c-1fec-4ba2-8fdb-d292f3327ba0",
            "Level": 1,
            "Type": "Intervention",
            "WorkItemId": "f9da57e0-bd09-46de-a037-063e6a5d6287",
            "Title": "42.5: Maintenance 2 Test I can assign task",
            "Client": null,
            "PlannedDate": "2020-12-15T00:00:00.000Z",
            "PlannedStartTime": null,
            "PlannedEndTime": null,
            "PlannedWorkload": 0.25,
            "Timesheets": 0,
            "Status": "Planned",
            "Color": null
        },
        {
            "Id": "5216a440-5d54-4215-a0fe-71f5b605eb24",
            "Level": 1,
            "Type": "Intervention",
            "WorkItemId": "c8bf0b44-878e-4e83-8c8b-43cf7a504712",
            "Title": "40.5: Test GF-436 test draft assignments",
            "Client": null,
            "PlannedDate": "2020-12-16T00:00:00.000Z",
            "PlannedStartTime": null,
            "PlannedEndTime": null,
            "PlannedWorkload": 3.25,
            "Timesheets": 0,
            "Status": "Planned",
            "Color": "#304100"
        },
        {
            "Id": "640b4f47-07ca-4a17-88f9-aa40df840263",
            "Level": 1,
            "Type": "Intervention",
            "WorkItemId": "c8bf0b44-878e-4e83-8c8b-43cf7a504712",
            "Title": "40.5: Test GF-436 test draft assignments",
            "Client": null,
            "PlannedDate": "2020-12-16T00:00:00.000Z",
            "PlannedStartTime": null,
            "PlannedEndTime": null,
            "PlannedWorkload": 0.25,
            "Timesheets": 0,
            "Status": "Planned",
            "Color": "#304100"
        },
        {
            "Id": "ca1db50b-54c2-4a29-84e3-49fa6404fc83",
            "Level": 1,
            "Type": "Intervention",
            "WorkItemId": "2eb5907d-84a5-4355-a41c-fd21eba9ee5e",
            "Title": "42.3: Maintenance 2",
            "Client": null,
            "PlannedDate": "2020-12-16T00:00:00.000Z",
            "PlannedStartTime": null,
            "PlannedEndTime": null,
            "PlannedWorkload": 2.25,
            "Timesheets": 0,
            "Status": "Planned",
            "Color": null
        },
        {
            "Id": "5dff8bb2-2740-44bb-b0b9-42342bd1020a",
            "Level": 1,
            "Type": "Intervention",
            "WorkItemId": "2eb5907d-84a5-4355-a41c-fd21eba9ee5e",
            "Title": "42.3: Maintenance 2",
            "Client": null,
            "PlannedDate": "2020-12-17T00:00:00.000Z",
            "PlannedStartTime": "15:00",
            "PlannedEndTime": null,
            "PlannedWorkload": 1.75,
            "Timesheets": 0,
            "Status": "Planned",
            "Color": null
        },
        {
            "Id": "e3480ba9-86fa-4fb7-ae56-039d5fe1cd61",
            "Level": 1,
            "Type": "Intervention",
            "WorkItemId": "fcc8aedd-8c96-4829-b09b-8f5093671add",
            "Title": "42.2: Maintenance 2",
            "Client": null,
            "PlannedDate": "2020-12-17T00:00:00.000Z",
            "PlannedStartTime": null,
            "PlannedEndTime": null,
            "PlannedWorkload": 5,
            "Timesheets": 0,
            "Status": "Requested",
            "Color": null
        },
        {
            "Id": "b382402a-8d37-48d6-b489-6e5e98800d21",
            "Level": 1,
            "Type": "Intervention",
            "WorkItemId": "c8bf0b44-878e-4e83-8c8b-43cf7a504712",
            "Title": "40.5: Test GF-436 test draft assignments",
            "Client": null,
            "PlannedDate": "2020-12-18T00:00:00.000Z",
            "PlannedStartTime": null,
            "PlannedEndTime": null,
            "PlannedWorkload": 0.25,
            "Timesheets": 0,
            "Status": "Planned",
            "Color": "#304100"
        },
        {
            "Id": "bd09bc81-c749-46e2-9a27-a699f9bc59b6",
            "Level": 1,
            "Type": "Intervention",
            "WorkItemId": "770d994a-1ed9-457f-b040-18665b24954e",
            "Title": "42.4: Maintenance 2",
            "Client": null,
            "PlannedDate": "2020-12-21T00:00:00.000Z",
            "PlannedStartTime": null,
            "PlannedEndTime": null,
            "PlannedWorkload": 5.25,
            "Timesheets": 0,
            "Status": "Requested",
            "Color": null
        },
        {
            "Id": "39669312-b2c1-4c5d-8e33-2c157ab14ae3",
            "Level": 1,
            "Type": "Intervention",
            "WorkItemId": "770d994a-1ed9-457f-b040-18665b24954e",
            "Title": "42.4: Maintenance 2",
            "Client": null,
            "PlannedDate": "2020-12-22T00:00:00.000Z",
            "PlannedStartTime": null,
            "PlannedEndTime": null,
            "PlannedWorkload": 6.75,
            "Timesheets": 0,
            "Status": "Requested",
            "Color": null
        },
        {
            "Id": "7980521b-daa0-4582-909c-fa5fb3349bfb",
            "Level": 1,
            "Type": "Intervention",
            "WorkItemId": "c9963778-1d2f-4243-99ac-21f3daa6a5fb",
            "Title": "49.1: schedule by due date",
            "Client": null,
            "PlannedDate": "2021-01-08T00:00:00.000Z",
            "PlannedStartTime": null,
            "PlannedEndTime": null,
            "PlannedWorkload": 0.25,
            "Timesheets": 0,
            "Status": "Requested",
            "Color": null
        },
        {
            "Id": "e5cb3843-d881-43ac-8963-65ab66a5d7e0",
            "Level": 1,
            "Type": "Intervention",
            "WorkItemId": "faf9a53f-89ed-497a-99e2-e7af66d5dbe6",
            "Title": "46.4: Maintenance 2",
            "Client": null,
            "PlannedDate": "2021-01-08T00:00:00.000Z",
            "PlannedStartTime": null,
            "PlannedEndTime": null,
            "PlannedWorkload": 0.25,
            "Timesheets": 0,
            "Status": "Requested",
            "Color": null
        },
        {
            "Id": "f572a2c3-b92d-4ac5-8868-22242bbdd763",
            "Level": 1,
            "Type": "Intervention",
            "WorkItemId": "bce0c665-1c25-4770-8a85-2705cdbd816a",
            "Title": "42.7: Test GF-388",
            "Client": null,
            "PlannedDate": "2021-01-08T00:00:00.000Z",
            "PlannedStartTime": null,
            "PlannedEndTime": null,
            "PlannedWorkload": 0.25,
            "Timesheets": 0,
            "Status": "Requested",
            "Color": null
        },
        {
            "Id": "9a43a5b5-d442-4dd8-bc0b-d843447a801d",
            "Level": 1,
            "Type": "Intervention",
            "WorkItemId": "4ef65729-d7e8-4301-a15b-02801eef0c6c",
            "Title": "46.2: Maintenance 2",
            "Client": null,
            "PlannedDate": "2021-01-08T00:00:00.000Z",
            "PlannedStartTime": null,
            "PlannedEndTime": null,
            "PlannedWorkload": 0.25,
            "Timesheets": 0,
            "Status": "Requested",
            "Color": null
        },
        {
            "Id": "8e84496b-e1c0-4a85-be95-4bf8b680275b",
            "Level": 1,
            "Type": "Intervention",
            "WorkItemId": "d037eb36-02e3-45d6-a14c-e060702cb5ba",
            "Title": "13.1: incident test 06/07 intervention",
            "Client": null,
            "PlannedDate": "2021-01-08T00:00:00.000Z",
            "PlannedStartTime": null,
            "PlannedEndTime": null,
            "PlannedWorkload": 7,
            "Timesheets": 0,
            "Status": "Requested",
            "Color": "#304100"
        },
        {
            "Id": "777c9b8d-0af1-4a7a-a6c4-7deff279ee02",
            "Level": 1,
            "Type": "Intervention",
            "WorkItemId": "147c02ff-6c30-422a-9004-a0f35ec9f8c2",
            "Title": "47.4: Maintenance 2",
            "Client": null,
            "PlannedDate": "2021-01-09T00:00:00.000Z",
            "PlannedStartTime": null,
            "PlannedEndTime": null,
            "PlannedWorkload": 0.25,
            "Timesheets": 0,
            "Status": "Requested",
            "Color": null
        },
        {
            "Id": "1b3e265f-1c59-4670-b14b-4a99a64183bf",
            "Level": 1,
            "Type": "Intervention",
            "WorkItemId": "c9963778-1d2f-4243-99ac-21f3daa6a5fb",
            "Title": "49.1: schedule by due date",
            "Client": null,
            "PlannedDate": "2021-01-11T00:00:00.000Z",
            "PlannedStartTime": null,
            "PlannedEndTime": null,
            "PlannedWorkload": 0.25,
            "Timesheets": 0,
            "Status": "Requested",
            "Color": null
        },
        {
            "Id": "315bf9c3-2a3e-4439-bd3f-d3689661ba07",
            "Level": 1,
            "Type": "Intervention",
            "WorkItemId": "faf9a53f-89ed-497a-99e2-e7af66d5dbe6",
            "Title": "46.4: Maintenance 2",
            "Client": null,
            "PlannedDate": "2021-01-11T00:00:00.000Z",
            "PlannedStartTime": null,
            "PlannedEndTime": null,
            "PlannedWorkload": 0.25,
            "Timesheets": 0,
            "Status": "Requested",
            "Color": null
        },
        {
            "Id": "7d912fee-e05a-4bc8-a4b6-78bccca3d063",
            "Level": 1,
            "Type": "Intervention",
            "WorkItemId": "2eb5907d-84a5-4355-a41c-fd21eba9ee5e",
            "Title": "42.3: Maintenance 2",
            "Client": null,
            "PlannedDate": "2021-01-11T00:00:00.000Z",
            "PlannedStartTime": null,
            "PlannedEndTime": null,
            "PlannedWorkload": 0.25,
            "Timesheets": 0,
            "Status": "Requested",
            "Color": null
        },
        {
            "Id": "51821d2d-7dca-48b2-9e7d-f82d04543fc4",
            "Level": 1,
            "Type": "Intervention",
            "WorkItemId": "6cb08dc3-62b6-4b37-aeaf-7cdc17e9320a",
            "Title": "40.1: Test GF-161 Intervener 1",
            "Client": null,
            "PlannedDate": "2021-01-11T00:00:00.000Z",
            "PlannedStartTime": null,
            "PlannedEndTime": null,
            "PlannedWorkload": 0.25,
            "Timesheets": 0,
            "Status": "Requested",
            "Color": "#304100"
        },
        {
            "Id": "f3b1115b-a165-483c-91f4-82e12cc47181",
            "Level": 1,
            "Type": "Intervention",
            "WorkItemId": "84b9b37a-b431-4167-8c9f-8baa48387911",
            "Title": "39.2: test 304_1111",
            "Client": null,
            "PlannedDate": "2021-01-11T00:00:00.000Z",
            "PlannedStartTime": null,
            "PlannedEndTime": null,
            "PlannedWorkload": 0.25,
            "Timesheets": 0,
            "Status": "Requested",
            "Color": null
        },
        {
            "Id": "0c913808-b427-4903-b22a-5625b77af524",
            "Level": 1,
            "Type": "Intervention",
            "WorkItemId": "51604432-453b-4119-a8a8-8329bfabe82a",
            "Title": "50.2: schedule by due date",
            "Client": null,
            "PlannedDate": "2021-01-11T00:00:00.000Z",
            "PlannedStartTime": null,
            "PlannedEndTime": null,
            "PlannedWorkload": 0.25,
            "Timesheets": 0,
            "Status": "Requested",
            "Color": null
        },
        {
            "Id": "8960bbcc-4573-430e-8a9b-83348e9fc238",
            "Level": 1,
            "Type": "Intervention",
            "WorkItemId": "147c02ff-6c30-422a-9004-a0f35ec9f8c2",
            "Title": "47.4: Maintenance 2",
            "Client": null,
            "PlannedDate": "2021-01-11T00:00:00.000Z",
            "PlannedStartTime": null,
            "PlannedEndTime": null,
            "PlannedWorkload": 0.25,
            "Timesheets": 0,
            "Status": "Requested",
            "Color": null
        },
        {
            "TotalCount": 14,
            "Name": "Today",
            "Level": 0
        },
        {
            "Id": "b2d1c265-c75b-4c70-af25-454b4d702eb9",
            "Level": 1,
            "Type": "Intervention",
            "WorkItemId": "51604432-453b-4119-a8a8-8329bfabe82a",
            "Title": "50.2: schedule by due date",
            "Client": null,
            "PlannedDate": "2021-01-12T00:00:00.000Z",
            "PlannedStartTime": null,
            "PlannedEndTime": null,
            "PlannedWorkload": 0.25,
            "Timesheets": 0,
            "Status": "Requested",
            "Color": null
        },
        {
            "Id": "6bac7833-898d-4638-81da-aba7e9ef6a5c",
            "Level": 1,
            "Type": "Intervention",
            "WorkItemId": "c9963778-1d2f-4243-99ac-21f3daa6a5fb",
            "Title": "49.1: schedule by due date",
            "Client": null,
            "PlannedDate": "2021-01-12T00:00:00.000Z",
            "PlannedStartTime": null,
            "PlannedEndTime": null,
            "PlannedWorkload": 0.25,
            "Timesheets": 0,
            "Status": "Requested",
            "Color": null
        },
        {
            "Id": "8db6ae8d-0019-47c0-a79b-d46d7a787003",
            "Level": 1,
            "Type": "Intervention",
            "WorkItemId": "147c02ff-6c30-422a-9004-a0f35ec9f8c2",
            "Title": "47.4: Maintenance 2",
            "Client": null,
            "PlannedDate": "2021-01-12T00:00:00.000Z",
            "PlannedStartTime": null,
            "PlannedEndTime": null,
            "PlannedWorkload": 0.25,
            "Timesheets": 0,
            "Status": "Requested",
            "Color": null
        },
        {
            "Id": "fe33677f-95f0-435e-9582-f2bcb3866a7d",
            "Level": 1,
            "Type": "Intervention",
            "WorkItemId": "cf6af115-198d-45b0-91b2-ce41da6514a6",
            "Title": "47.2: Maintenance 2",
            "Client": null,
            "PlannedDate": "2021-01-12T00:00:00.000Z",
            "PlannedStartTime": null,
            "PlannedEndTime": null,
            "PlannedWorkload": 0.25,
            "Timesheets": 0,
            "Status": "Requested",
            "Color": null
        },
        {
            "Id": "53d20366-11bf-49d5-ba60-12ba75abd67b",
            "Level": 1,
            "Type": "Intervention",
            "WorkItemId": "faf9a53f-89ed-497a-99e2-e7af66d5dbe6",
            "Title": "46.4: Maintenance 2",
            "Client": null,
            "PlannedDate": "2021-01-12T00:00:00.000Z",
            "PlannedStartTime": null,
            "PlannedEndTime": null,
            "PlannedWorkload": 0.25,
            "Timesheets": 0,
            "Status": "Requested",
            "Color": null
        },
        {
            "Id": "11252d27-d54f-48f5-ae11-39d3a8da70c3",
            "Level": 1,
            "Type": "Intervention",
            "WorkItemId": "4ef65729-d7e8-4301-a15b-02801eef0c6c",
            "Title": "46.2: Maintenance 2",
            "Client": null,
            "PlannedDate": "2021-01-12T00:00:00.000Z",
            "PlannedStartTime": null,
            "PlannedEndTime": null,
            "PlannedWorkload": 0.25,
            "Timesheets": 0,
            "Status": "Requested",
            "Color": null
        },
        {
            "Id": "61ecba3e-5ab9-4198-af7b-38d7b7897919",
            "Level": 1,
            "Type": "Intervention",
            "WorkItemId": "c96bd927-160e-4700-8415-95846b5a4a17",
            "Title": "45.1: My schedule",
            "Client": null,
            "PlannedDate": "2021-01-12T00:00:00.000Z",
            "PlannedStartTime": null,
            "PlannedEndTime": null,
            "PlannedWorkload": 0.25,
            "Timesheets": 0,
            "Status": "Requested",
            "Color": null
        },
        {
            "Id": "ecfef8fc-8bf8-4457-950e-8fa99dc3ac47",
            "Level": 1,
            "Type": "Intervention",
            "WorkItemId": "bce0c665-1c25-4770-8a85-2705cdbd816a",
            "Title": "42.7: Test GF-388",
            "Client": null,
            "PlannedDate": "2021-01-12T00:00:00.000Z",
            "PlannedStartTime": null,
            "PlannedEndTime": null,
            "PlannedWorkload": 0.25,
            "Timesheets": 0,
            "Status": "Requested",
            "Color": null
        },
        {
            "Id": "72f9ae4a-8188-4c9b-9aa8-986d4fefb535",
            "Level": 1,
            "Type": "Intervention",
            "WorkItemId": "f9da57e0-bd09-46de-a037-063e6a5d6287",
            "Title": "42.5: Maintenance 2 Test I can assign task",
            "Client": null,
            "PlannedDate": "2021-01-12T00:00:00.000Z",
            "PlannedStartTime": null,
            "PlannedEndTime": null,
            "PlannedWorkload": 0.25,
            "Timesheets": 0,
            "Status": "Requested",
            "Color": null
        },
        {
            "Id": "324e7e1e-a801-472f-8917-80118d75264d",
            "Level": 1,
            "Type": "Intervention",
            "WorkItemId": "770d994a-1ed9-457f-b040-18665b24954e",
            "Title": "42.4: Maintenance 2",
            "Client": null,
            "PlannedDate": "2021-01-12T00:00:00.000Z",
            "PlannedStartTime": null,
            "PlannedEndTime": null,
            "PlannedWorkload": 0.25,
            "Timesheets": 0,
            "Status": "Requested",
            "Color": null
        },
        {
            "Id": "7b48cef1-4d4d-4dd3-959e-bd7573376bf6",
            "Level": 1,
            "Type": "Intervention",
            "WorkItemId": "2eb5907d-84a5-4355-a41c-fd21eba9ee5e",
            "Title": "42.3: Maintenance 2",
            "Client": null,
            "PlannedDate": "2021-01-12T00:00:00.000Z",
            "PlannedStartTime": null,
            "PlannedEndTime": null,
            "PlannedWorkload": 0.25,
            "Timesheets": 0,
            "Status": "Requested",
            "Color": null
        },
        {
            "Id": "c3b950ef-897f-4393-9c58-aa23f429501f",
            "Level": 1,
            "Type": "Intervention",
            "WorkItemId": "fcc8aedd-8c96-4829-b09b-8f5093671add",
            "Title": "42.2: Maintenance 2",
            "Client": null,
            "PlannedDate": "2021-01-12T00:00:00.000Z",
            "PlannedStartTime": null,
            "PlannedEndTime": null,
            "PlannedWorkload": 0.25,
            "Timesheets": 0,
            "Status": "Requested",
            "Color": null
        },
        {
            "Id": "9a731f54-a4e2-4301-bd99-1c397ff5758b",
            "Level": 1,
            "Type": "Intervention",
            "WorkItemId": "efe86bf8-16d5-4fae-95e7-d09fd6786443",
            "Title": "42.1: Sicosport",
            "Client": null,
            "PlannedDate": "2021-01-12T00:00:00.000Z",
            "PlannedStartTime": null,
            "PlannedEndTime": null,
            "PlannedWorkload": 0.25,
            "Timesheets": 0,
            "Status": "Requested",
            "Color": null
        },
        {
            "Id": "cb1d7c9c-29f2-4030-bbb9-6e0cc9a30f63",
            "Level": 1,
            "Type": "Intervention",
            "WorkItemId": "05e04782-0063-4c18-b326-a78b779a6814",
            "Title": "41.4: Maintenance 2",
            "Client": null,
            "PlannedDate": "2021-01-12T00:00:00.000Z",
            "PlannedStartTime": null,
            "PlannedEndTime": null,
            "PlannedWorkload": 0.25,
            "Timesheets": 0,
            "Status": "Requested",
            "Color": null
        },
        {
            "TotalCount": 8,
            "Name": "Tomorrow",
            "Level": 0
        },
        {
            "Id": "3ab5c523-aec9-4d49-be8f-7b532d025785",
            "Level": 1,
            "Type": "Intervention",
            "WorkItemId": "c8bf0b44-878e-4e83-8c8b-43cf7a504712",
            "Title": "40.5: Test GF-436 test draft assignments",
            "Client": null,
            "PlannedDate": "2021-01-13T00:00:00.000Z",
            "PlannedStartTime": null,
            "PlannedEndTime": null,
            "PlannedWorkload": 0.25,
            "Timesheets": 0,
            "Status": "Requested",
            "Color": "#304100"
        },
        {
            "Id": "877265ea-aa92-4adc-9d21-e38201a17da5",
            "Level": 1,
            "Type": "Intervention",
            "WorkItemId": "22018682-105d-4732-baaf-a4ac8615a3a2",
            "Title": "40.4: Test GF-161 111111",
            "Client": null,
            "PlannedDate": "2021-01-13T00:00:00.000Z",
            "PlannedStartTime": null,
            "PlannedEndTime": null,
            "PlannedWorkload": 0.25,
            "Timesheets": 0,
            "Status": "Requested",
            "Color": "#304100"
        },
        {
            "Id": "238c5980-d3ef-479f-8621-4aed3347ec6b",
            "Level": 1,
            "Type": "Intervention",
            "WorkItemId": "6cb08dc3-62b6-4b37-aeaf-7cdc17e9320a",
            "Title": "40.1: Test GF-161 Intervener 1",
            "Client": null,
            "PlannedDate": "2021-01-13T00:00:00.000Z",
            "PlannedStartTime": null,
            "PlannedEndTime": null,
            "PlannedWorkload": 0.25,
            "Timesheets": 0,
            "Status": "Requested",
            "Color": "#304100"
        },
        {
            "Id": "61d7886b-dac0-4756-952c-ae64382cfa72",
            "Level": 1,
            "Type": "Intervention",
            "WorkItemId": "84b9b37a-b431-4167-8c9f-8baa48387911",
            "Title": "39.2: test 304_1111",
            "Client": null,
            "PlannedDate": "2021-01-13T00:00:00.000Z",
            "PlannedStartTime": null,
            "PlannedEndTime": null,
            "PlannedWorkload": 0.25,
            "Timesheets": 0,
            "Status": "Requested",
            "Color": null
        },
        {
            "Id": "3b1b34e4-2e96-468e-bfef-1559b576254a",
            "Level": 1,
            "Type": "Task",
            "WorkItemId": "f7c4552e-a617-4b7f-bfc1-0d9043fb6627",
            "Title": "Task for notification 111",
            "Client": null,
            "PlannedDate": "2021-01-13T00:00:00.000Z",
            "PlannedStartTime": null,
            "PlannedEndTime": null,
            "PlannedWorkload": 0.25,
            "Timesheets": 0,
            "Status": "Requested",
            "Color": null
        },
        {
            "Id": "9c14a893-c67e-4ffb-bae1-be5d3d5da938",
            "Level": 1,
            "Type": "Intervention",
            "WorkItemId": "c9963778-1d2f-4243-99ac-21f3daa6a5fb",
            "Title": "49.1: schedule by due date",
            "Client": null,
            "PlannedDate": "2021-01-13T00:00:00.000Z",
            "PlannedStartTime": null,
            "PlannedEndTime": null,
            "PlannedWorkload": 0.25,
            "Timesheets": 0,
            "Status": "Requested",
            "Color": null
        },
        {
            "Id": "d283abae-24d3-471c-9cf5-104a098361fc",
            "Level": 1,
            "Type": "Intervention",
            "WorkItemId": "cf6af115-198d-45b0-91b2-ce41da6514a6",
            "Title": "47.2: Maintenance 2",
            "Client": null,
            "PlannedDate": "2021-01-13T00:00:00.000Z",
            "PlannedStartTime": null,
            "PlannedEndTime": null,
            "PlannedWorkload": 0.25,
            "Timesheets": 0,
            "Status": "Requested",
            "Color": null
        },
        {
            "Id": "6b1d2f0f-5d35-4027-b224-317a2e263289",
            "Level": 1,
            "Type": "Intervention",
            "WorkItemId": "4ef65729-d7e8-4301-a15b-02801eef0c6c",
            "Title": "46.2: Maintenance 2",
            "Client": null,
            "PlannedDate": "2021-01-13T00:00:00.000Z",
            "PlannedStartTime": null,
            "PlannedEndTime": null,
            "PlannedWorkload": 0.25,
            "Timesheets": 0,
            "Status": "Requested",
            "Color": null
        },
        {
            "TotalCount": 3,
            "Name": "Upcoming",
            "Level": 0
        },
        {
            "Id": "2bce8250-e5c6-4217-8fd3-a0811ca4c252",
            "Level": 1,
            "Type": "Intervention",
            "WorkItemId": "cf6af115-198d-45b0-91b2-ce41da6514a6",
            "Title": "47.2: Maintenance 2",
            "Client": null,
            "PlannedDate": "2021-01-14T00:00:00.000Z",
            "PlannedStartTime": null,
            "PlannedEndTime": null,
            "PlannedWorkload": 0.25,
            "Timesheets": 0,
            "Status": "Requested",
            "Color": null
        },
        {
            "Id": "89ef6ba0-59ef-4a33-902b-ffe36d8127bf",
            "Level": 1,
            "Type": "Intervention",
            "WorkItemId": "4ef65729-d7e8-4301-a15b-02801eef0c6c",
            "Title": "46.2: Maintenance 2",
            "Client": null,
            "PlannedDate": "2021-01-15T00:00:00.000Z",
            "PlannedStartTime": null,
            "PlannedEndTime": null,
            "PlannedWorkload": 0.25,
            "Timesheets": 0,
            "Status": "Requested",
            "Color": null
        },
        {
            "Id": "333a1941-43ab-47b2-a956-e2c8fdc6d99c",
            "Level": 1,
            "Type": "Intervention",
            "WorkItemId": "147c02ff-6c30-422a-9004-a0f35ec9f8c2",
            "Title": "47.4: Maintenance 2",
            "Client": null,
            "PlannedDate": "2021-01-19T00:00:00.000Z",
            "PlannedStartTime": null,
            "PlannedEndTime": null,
            "PlannedWorkload": 0.25,
            "Timesheets": 0,
            "Status": "Requested",
            "Color": null
        },
        {
            "TotalCount": 2,
            "Name": "Future",
            "Level": 0
        },
        {
            "Id": "56f54691-37d4-4f4e-9f8a-c2cc570b1e79",
            "Level": 1,
            "Type": "Intervention",
            "WorkItemId": "51604432-453b-4119-a8a8-8329bfabe82a",
            "Title": "50.2: schedule by due date",
            "Client": null,
            "PlannedDate": "2021-01-21T00:00:00.000Z",
            "PlannedStartTime": null,
            "PlannedEndTime": null,
            "PlannedWorkload": 0.25,
            "Timesheets": 0,
            "Status": "Requested",
            "Color": null
        },
        {
            "Id": "2996674e-d135-4b62-b72c-742a719277bb",
            "Level": 1,
            "Type": "Intervention",
            "WorkItemId": "faf9a53f-89ed-497a-99e2-e7af66d5dbe6",
            "Title": "46.4: Maintenance 2",
            "Client": null,
            "PlannedDate": "2021-01-21T00:00:00.000Z",
            "PlannedStartTime": null,
            "PlannedEndTime": null,
            "PlannedWorkload": 0.25,
            "Timesheets": 0,
            "Status": "Requested",
            "Color": null
        }
    ]
}